<Properties StartupConfiguration="{1902913C-BB6F-4CCB-9B90-1D0CAEECAF12}|Default">
  <MonoDevelop.Ide.Workbench ActiveDocument="Todo/Views/LandingPageCS.cs">
    <Files>
      <File FileName="Todo.iOS/Entitlements.plist" />
      <File FileName="Todo.iOS/AppDelegate.cs" Line="1" Column="1" />
      <File FileName="Todo.iOS/Info.plist" />
      <File FileName="Todo/Views/LandingPage.xaml" Line="16" Column="55" />
      <File FileName="Todo/Views/LandingPageCS.cs" Line="7" Column="7" />
      <File FileName="Todo/Views/ScanPage.xaml" Line="10" Column="46" />
      <File FileName="Todo/Views/ScanPage.xaml.cs" Line="15" Column="53" />
    </Files>
    <Pads>
      <Pad Id="ProjectPad">
        <State name="__root__">
          <Node name="Todo" expanded="True">
            <Node name="Targets" expanded="True">
              <Node name="Todo.iOS" expanded="True" />
            </Node>
            <Node name="Todo" expanded="True">
              <Node name="Dependencies" expanded="True">
                <Node name="PackageDependencies" expanded="True" />
                <Node name="SdkDependencies" expanded="True" />
              </Node>
              <Node name="Data" expanded="True" />
              <Node name="Models" expanded="True" />
              <Node name="Views" expanded="True">
                <Node name="LandingPageCS.cs" selected="True" />
              </Node>
            </Node>
          </Node>
        </State>
      </Pad>
    </Pads>
  </MonoDevelop.Ide.Workbench>
  <MonoDevelop.Ide.DebuggingService.PinnedWatches />
  <MonoDevelop.Ide.Workspace ActiveConfiguration="Release|iPhone" />
  <MonoDevelop.Ide.ItemProperties.Targets.Todo.iOS automaticSigning="True" PreferredExecutionTarget="MonoDevelop.IPhone.IPhoneDeviceTarget">
    <MonoDevelop.MacDev.AppleDevelopmentTeam DeveloperId="97Z8S792NU" TeamId="K6R355V4D8" />
  </MonoDevelop.Ide.ItemProperties.Targets.Todo.iOS>
  <MonoDevelop.Ide.DebuggingService.Breakpoints>
    <BreakpointStore />
  </MonoDevelop.Ide.DebuggingService.Breakpoints>
  <MultiItemStartupConfigurations />
</Properties>